{
  "type": "article",
  "subtype": "mcms",
  "id": 63314856,
  "author": "Rita Pierotti",
  "title": "Plano Indexado: a melhor estratégia para aposentadoria ",
  "date": "2022-03-26T23:30:00+01:00",
  "leadin": "",
  "summary": "​Plano Indexado, melhor estratégia para sua aposentadoria com Gustavo Couto.",
  "content": " <div class=\"photo top\" style=\"text-align:center\"> <a href=\"https://cmsphoto.ww-cdn.com/superstatic/2009698/art/grande/63314856-58477156.jpg?v=1718916554\" target=\"_blank\"> <img id=\"img-63314856-58477156\" src=\"https://cmsphoto.ww-cdn.com/superstatic/2009698/art/default/63314856-58477156.jpg?v=1718916555\" alt=\"Plano Indexado: a melhor estratégia para aposentadoria \" title=\"Plano Indexado: a melhor estratégia para aposentadoria \" /> </a> </div> <br class=\"clear\" /> <iframe src=\"https://player.vimeo.com/video/692416648?h=442d989275\" width=\"640\" height=\"360\" frameborder=\"0\" allow=\"autoplay; fullscreen; picture-in-picture\" allowfullscreen></iframe> <div class=\"texte\" > <p>​Plano Indexado, melhor estratégia para sua aposentadoria com Gustavo Couto.</p> <p>&nbsp;</p> </div> <br class=\"clear\" /> ",
  "images": [
    {
      "id": "img-63314856-58477156",
      "url": "https://cmsphoto.ww-cdn.com/superstatic/2009698/art/default/63314856-58477156.jpg?v=1718916555",
      "otherImagesUrl": {
        "large": "https://cmsphoto.ww-cdn.com/superstatic/2009698/art/grande/63314856-58477156.jpg?v=1718916554"
      }
    }
  ],
  "isFeatured": "img-63314856-58477156",
  "smallThumbnail": "https://cmsphoto.ww-cdn.com/resizeapi/3475c79c132d7d38e0418df518eb2d9039de7ce1/157/93/",
  "thumbnail": "https://cmsphoto.ww-cdn.com/resizeapi/3475c79c132d7d38e0418df518eb2d9039de7ce1/314/196/",
  "originalThumbnail": "https://cmsphoto.ww-cdn.com/superstatic/2009698/art/grande/63314856-58477156.jpg?v=1718916554",
  "largeThumbnail": "https://cmsphoto.ww-cdn.com/resizeapi/3475c79c132d7d38e0418df518eb2d9039de7ce1/750/-1/",
  "xLargeThumbnail": "https://cmsphoto.ww-cdn.com/resizeapi/3475c79c132d7d38e0418df518eb2d9039de7ce1/1200/-1/",
  "xxLargeThumbnail": "https://cmsphoto.ww-cdn.com/resizeapi/3475c79c132d7d38e0418df518eb2d9039de7ce1/3200/-1/",
  "latitude": "0",
  "longitude": "0",
  "subtitle": "",
  "isHeadline": 0,
  "authorAvatarUrl": "",
  "slug": "copy-bootcamp-04092021-plano-indexado-melhor-estrategia-para-sua-aposentadoria-ii",
  "meta": {
    "title": "",
    "description": ""
  },
  "commentsEnabled": true,
  "commentsPostUrl": "https://brazillionaires.virtualnet.site/apiv3/submitComment/64072908/63314856/?username=[name]&comment=[content]&email=[email]",
  "commentsUrl": "https://brazillionaires.virtualnet.site/apiv3/getCommentsByItem/64072908/63314856/1/24/",
  "nbcomments": 0,
  "url": "https://brazillionaires.virtualnet.site/estrategia/i/63314856/copy-bootcamp-04092021-plano-indexado-melhor-estrategia-para-sua-aposentadoria-ii",
  "subsections": {
    "49033606": [
      "Categoria principal"
    ],
    "64072908": [
      "Categoria principal"
    ]
  }
}