{
  "type": "article",
  "subtype": "mcms",
  "id": 88097934,
  "author": "Rogerio Bonfim",
  "title": "Power Monday  - Para ficar rico, ajude mais pessoas!",
  "date": "2025-03-10T18:06:00+01:00",
  "leadin": "",
  "summary": "Power Monday 04-21-2025 - Para ficar rico, ajude mais pessoas!",
  "content": " <div class=\"photo top\" style=\"text-align:center\"> <a href=\"https://cmsphoto.ww-cdn.com/superstatic/2009698/art/grande/88097934-62397514.jpg?v=1745428029\" target=\"_blank\"> <img id=\"img-88097934-62397514\" src=\"https://cmsphoto.ww-cdn.com/superstatic/2009698/art/default/88097934-62397514.jpg?v=1745428029\" alt=\"Power Monday - Para ficar rico, ajude mais pessoas!\" title=\"Power Monday - Para ficar rico, ajude mais pessoas!\" /> </a> </div> <br class=\"clear\" /> <iframe src=\"https://player.vimeo.com/video/1077315642?title=0&byline=0&portrait=0&badge=0&autopause=0&player_id=0&app_id=58479\" width=\"1920\" height=\"1080\" frameborder=\"0\" allow=\"autoplay; fullscreen; picture-in-picture; clipboard-write; encrypted-media\" title=\"Power Monday 04-21-2025 - Para ficar rico, ajude mais pessoas\"></iframe> <div class=\"texte\" > <p>Power Monday 04-21-2025 - Para ficar rico, ajude mais pessoas!</p> </div> <br class=\"clear\" /> ",
  "images": [
    {
      "id": "img-88097934-62397514",
      "url": "https://cmsphoto.ww-cdn.com/superstatic/2009698/art/default/88097934-62397514.jpg?v=1745428029",
      "otherImagesUrl": {
        "large": "https://cmsphoto.ww-cdn.com/superstatic/2009698/art/grande/88097934-62397514.jpg?v=1745428029"
      }
    }
  ],
  "isFeatured": "img-88097934-62397514",
  "smallThumbnail": "https://cmsphoto.ww-cdn.com/resizeapi/7be21089bb645f48258f1c4e1034365444f9f0cf/157/93/",
  "thumbnail": "https://cmsphoto.ww-cdn.com/resizeapi/7be21089bb645f48258f1c4e1034365444f9f0cf/314/196/",
  "originalThumbnail": "https://cmsphoto.ww-cdn.com/superstatic/2009698/art/grande/88097934-62397514.jpg?v=1745428029",
  "largeThumbnail": "https://cmsphoto.ww-cdn.com/resizeapi/7be21089bb645f48258f1c4e1034365444f9f0cf/750/-1/",
  "xLargeThumbnail": "https://cmsphoto.ww-cdn.com/resizeapi/7be21089bb645f48258f1c4e1034365444f9f0cf/1200/-1/",
  "xxLargeThumbnail": "https://cmsphoto.ww-cdn.com/resizeapi/7be21089bb645f48258f1c4e1034365444f9f0cf/3200/-1/",
  "latitude": "0",
  "longitude": "0",
  "subtitle": "",
  "isHeadline": 0,
  "authorAvatarUrl": "",
  "slug": "article-5395",
  "meta": {
    "title": "",
    "description": ""
  },
  "commentsEnabled": true,
  "commentsPostUrl": "https://brazillionaires.virtualnet.site/apiv3/submitComment/65604413/88097934/?username=[name]&comment=[content]&email=[email]",
  "commentsUrl": "https://brazillionaires.virtualnet.site/apiv3/getCommentsByItem/65604413/88097934/1/24/",
  "nbcomments": 0,
  "url": "https://brazillionaires.virtualnet.site/bonus/i/88097934/article-5395",
  "subsections": {
    "65604413": [
      "Categoria principal"
    ]
  }
}